setup.py
KrislavLibraryPy/__init__.py
KrislavLibraryPy/caesar_cipher.py
KrislavLibraryPy/convert.py
KrislavLibraryPy/test.py
KrislavLibraryPy.egg-info/PKG-INFO
KrislavLibraryPy.egg-info/SOURCES.txt
KrislavLibraryPy.egg-info/dependency_links.txt
KrislavLibraryPy.egg-info/top_level.txt