Metadata-Version: 2.1
Name: KrislavLibraryPy
Version: 0.2.0
Summary: Python module for my own use
Author: Krislav
Author-email: kirill.sokolyansky@gmail.com
